[
  {
    "title": "detik-Indonesia",
    "image": "/clients/detik-Indonesia.jpg",
    "link": "#"
  },
  {
    "title": "detik-papua-logo",
    "image": "/clients/detik-papua-logo.jpg",
    "link": "#"
  },
  {
    "title": "logo-progresif",
    "image": "/clients/logo-progresif.jpg",
    "link": "#"
  },
  {
    "title": "republik-kieraha",
    "image": "/clients/republik-kieraha.jpg",
    "link": "#"
  },
  {
    "title": "detiknusantara",
    "image": "/clients/detiknusantara.jpg",
    "link": "#"
  },
  {
    "title": "Lentera-Faktual",
    "image": "/clients/Lentera-Faktual.jpg",
    "link": "#"
  },
  {
    "title": "zabak",
    "image": "/clients/zabak.jpg",
    "link": "#"
  },
  {
    "title": "metapolitik",
    "image": "/clients/metapolitik.jpg",
    "link": "#"
  }
]